[
  {
    "mean_test_accuracy": 0.9899999999999999,
    "mean_test_loss": 0.09668883542616787,
    "mean_threshold": 0.3670358109961465,
    "mean_train_accuracy": 1.0,
    "mean_train_loss": 0.08663998634596097,
    "num_runs": 3,
    "phase_diagram_path": "/scratch/users/jdehoney/eqnn_thesis/data/reproduction/paper_reproduction_19973403/n9/train_size_8/phase_diagrams/train_size_8_phase_diagram.npz",
    "train_size": 8,
    "variance_test_accuracy": 1.232595164407831e-32,
    "variance_test_loss": 1.944584265615176e-09,
    "variance_threshold": 4.039915758205072e-06,
    "variance_train_accuracy": 0.0,
    "variance_train_loss": 1.8355613435404916e-11
  }
]
