{
  "classification_threshold": 0.4328404174567465,
  "dataset_metadata": {
    "boundary": "open",
    "critical_ratio": 1.0,
    "dataset_name": "bond_alternating_heisenberg_paper_reproduction_v1",
    "dense_test_points_requested": 101,
    "dense_test_points_used": 100,
    "eigensolver_requested": "auto",
    "eigensolver_resolved": "dense",
    "label_convention": "paper_reproduction_v1_swap_aligned",
    "left_ratio_min": 0.0,
    "notes": [
      "This dataset is locked to the paper_reproduction_v1 protocol.",
      "The training grid is symmetric around the critical ratio so every train set spans both phases.",
      "The dense test grid omits the exact critical point to keep labels unambiguous.",
      "Paper reproduction labels are aligned with the SWAP readout direction: larger outputs map to the trivial phase."
    ],
    "num_qubits": 6,
    "phase_labels": {
      "0": "topological phase (coupling_ratio > critical_ratio)",
      "1": "trivial phase (coupling_ratio < critical_ratio)"
    },
    "protocol": "paper_reproduction_v1",
    "right_ratio_max": 2.0,
    "test_ratios": [
      0.0,
      0.02,
      0.04,
      0.06,
      0.08,
      0.1,
      0.12,
      0.14,
      0.16,
      0.18,
      0.2,
      0.22,
      0.24,
      0.26,
      0.28,
      0.3,
      0.32,
      0.34,
      0.36,
      0.38,
      0.4,
      0.42,
      0.44,
      0.46,
      0.48,
      0.5,
      0.52,
      0.54,
      0.56,
      0.58,
      0.6,
      0.62,
      0.64,
      0.66,
      0.68,
      0.7000000000000001,
      0.72,
      0.74,
      0.76,
      0.78,
      0.8,
      0.8200000000000001,
      0.84,
      0.86,
      0.88,
      0.9,
      0.92,
      0.9400000000000001,
      0.96,
      0.98,
      1.02,
      1.04,
      1.06,
      1.08,
      1.1,
      1.12,
      1.1400000000000001,
      1.16,
      1.18,
      1.2,
      1.22,
      1.24,
      1.26,
      1.28,
      1.3,
      1.32,
      1.34,
      1.36,
      1.3800000000000001,
      1.4000000000000001,
      1.42,
      1.44,
      1.46,
      1.48,
      1.5,
      1.52,
      1.54,
      1.56,
      1.58,
      1.6,
      1.62,
      1.6400000000000001,
      1.6600000000000001,
      1.68,
      1.7,
      1.72,
      1.74,
      1.76,
      1.78,
      1.8,
      1.82,
      1.84,
      1.86,
      1.8800000000000001,
      1.9000000000000001,
      1.92,
      1.94,
      1.96,
      1.98,
      2.0
    ],
    "train_ratios": [
      0.16666666666666666,
      0.3333333333333333,
      0.5,
      0.6666666666666666,
      0.8333333333333333,
      1.1666666666666667,
      1.3333333333333333,
      1.5,
      1.6666666666666665,
      1.8333333333333333
    ],
    "train_size": 10
  },
  "experiment_config": {
    "backend_name": "torch_pure",
    "boundary": "open",
    "min_readout_qubits": null,
    "model_family": "su2_qcnn",
    "num_qubits": 6,
    "parity_sequence": [
      "even",
      "odd"
    ],
    "pooling_keep": "left",
    "pooling_mode": "partial_trace",
    "readout_mode": "swap",
    "shared_convolution_parameter": true
  },
  "experiment_name": "calibration_su2_qcnn_torch_pure_n6_train10_epochs50_seed1",
  "history": {
    "accuracy": [
      0.5,
      0.0,
      0.0,
      0.0,
      0.9,
      0.7,
      1.0,
      1.0,
      1.0,
      1.0,
      1.0,
      1.0,
      1.0,
      1.0,
      1.0,
      1.0,
      1.0,
      1.0,
      1.0,
      1.0,
      1.0,
      1.0,
      1.0,
      1.0,
      1.0,
      1.0,
      1.0,
      1.0,
      1.0,
      1.0,
      1.0,
      1.0,
      1.0,
      1.0,
      1.0,
      1.0,
      1.0,
      1.0,
      1.0,
      1.0,
      1.0,
      1.0,
      1.0,
      1.0,
      1.0,
      1.0,
      1.0,
      1.0,
      1.0,
      1.0,
      1.0
    ],
    "best_accuracy": 1.0,
    "best_loss": 0.10686030037347785,
    "best_parameters": [
      0.7397800246624819,
      -0.1306130652891606,
      -1.815618038815187,
      0.6931373891382923,
      0.04526779307828986
    ],
    "best_restart": 0,
    "best_threshold": 0.4328404174567465,
    "final_parameters": [
      0.7386258455542247,
      -0.14878930519867262,
      -1.7969795356166418,
      0.6862284996883247,
      0.04526779307233496
    ],
    "final_threshold": 0.42113301437857587,
    "initial_parameters": [
      0.017279209603239302,
      0.04108090717505792,
      0.016521853809169356,
      -0.06515786158021805,
      0.04526779333365589
    ],
    "loss": [
      0.44498885089882434,
      0.37025922727530136,
      0.34567404151320735,
      0.32837957968578946,
      0.2950739770810625,
      0.30418291969051986,
      0.26217247220189316,
      0.2343720766670052,
      0.19236534001834876,
      0.16189876375979625,
      0.13948583669519593,
      0.12335032074598226,
      0.12056106357737377,
      0.1125925989940213,
      0.11008879305633852,
      0.10997234717991944,
      0.1095074826394357,
      0.10776792998880638,
      0.10713829860892021,
      0.10717479444839484,
      0.10701168238568133,
      0.10698000284010875,
      0.10735308617046187,
      0.10720021212842985,
      0.10686689635117703,
      0.10748113179161689,
      0.10689843976649549,
      0.10690291130065352,
      0.10689860731929073,
      0.10692544636956511,
      0.10686968749884598,
      0.10686883188132443,
      0.10686649217975752,
      0.10691561249797894,
      0.10686030037347785,
      0.1069519966852838,
      0.10700292752410152,
      0.10714623393773048,
      0.10694190854192676,
      0.10686533645506664,
      0.1068933731742365,
      0.10686589387195289,
      0.10719037367485847,
      0.10693478840619944,
      0.10691047187733502,
      0.10701894171866236,
      0.10715483429268288,
      0.10706094189160617,
      0.10691627218677409,
      0.10689597914563484,
      0.10719890307803379
    ],
    "restart_histories": [
      {
        "accuracy": [
          0.5,
          0.0,
          0.0,
          0.0,
          0.9,
          0.7,
          1.0,
          1.0,
          1.0,
          1.0,
          1.0,
          1.0,
          1.0,
          1.0,
          1.0,
          1.0,
          1.0,
          1.0,
          1.0,
          1.0,
          1.0,
          1.0,
          1.0,
          1.0,
          1.0,
          1.0,
          1.0,
          1.0,
          1.0,
          1.0,
          1.0,
          1.0,
          1.0,
          1.0,
          1.0,
          1.0,
          1.0,
          1.0,
          1.0,
          1.0,
          1.0,
          1.0,
          1.0,
          1.0,
          1.0,
          1.0,
          1.0,
          1.0,
          1.0,
          1.0,
          1.0
        ],
        "best_accuracy": 1.0,
        "best_loss": 0.10686030037347785,
        "best_parameters": [
          0.7397800246624819,
          -0.1306130652891606,
          -1.815618038815187,
          0.6931373891382923,
          0.04526779307828986
        ],
        "best_threshold": 0.4328404174567465,
        "final_parameters": [
          0.7386258455542247,
          -0.14878930519867262,
          -1.7969795356166418,
          0.6862284996883247,
          0.04526779307233496
        ],
        "final_threshold": 0.42113301437857587,
        "initial_parameters": [
          0.017279209603239302,
          0.04108090717505792,
          0.016521853809169356,
          -0.06515786158021805,
          0.04526779333365589
        ],
        "loss": [
          0.44498885089882434,
          0.37025922727530136,
          0.34567404151320735,
          0.32837957968578946,
          0.2950739770810625,
          0.30418291969051986,
          0.26217247220189316,
          0.2343720766670052,
          0.19236534001834876,
          0.16189876375979625,
          0.13948583669519593,
          0.12335032074598226,
          0.12056106357737377,
          0.1125925989940213,
          0.11008879305633852,
          0.10997234717991944,
          0.1095074826394357,
          0.10776792998880638,
          0.10713829860892021,
          0.10717479444839484,
          0.10701168238568133,
          0.10698000284010875,
          0.10735308617046187,
          0.10720021212842985,
          0.10686689635117703,
          0.10748113179161689,
          0.10689843976649549,
          0.10690291130065352,
          0.10689860731929073,
          0.10692544636956511,
          0.10686968749884598,
          0.10686883188132443,
          0.10686649217975752,
          0.10691561249797894,
          0.10686030037347785,
          0.1069519966852838,
          0.10700292752410152,
          0.10714623393773048,
          0.10694190854192676,
          0.10686533645506664,
          0.1068933731742365,
          0.10686589387195289,
          0.10719037367485847,
          0.10693478840619944,
          0.10691047187733502,
          0.10701894171866236,
          0.10715483429268288,
          0.10706094189160617,
          0.10691627218677409,
          0.10689597914563484,
          0.10719890307803379
        ],
        "threshold": [
          0.5,
          0.7970087121458014,
          0.7844091564554196,
          0.7625829494114857,
          0.7433470452905854,
          0.7637865951080034,
          0.6940274118400376,
          0.6082159378748027,
          0.4580116688396677,
          0.37899830668896156,
          0.3496821871191637,
          0.4030722932659391,
          0.44754879915280976,
          0.42400414591068214,
          0.4185906551933077,
          0.4336249431015812,
          0.4430122412815192,
          0.43026733369131187,
          0.43157827491938083,
          0.4382800511337648,
          0.43342127039482387,
          0.42754620666238613,
          0.4177735466397125,
          0.42015024082910823,
          0.43129560695572017,
          0.4501790297427924,
          0.43755146614348894,
          0.4335797491732146,
          0.43463774914214276,
          0.429007056195842,
          0.43114671745302907,
          0.43353893692739764,
          0.4329663899208686,
          0.43787112504238906,
          0.4328404174567465,
          0.44011578880696833,
          0.44191777293136614,
          0.42356781579837766,
          0.4285146987744168,
          0.433109503913006,
          0.4289835098039974,
          0.4327849662972265,
          0.4447872008170273,
          0.4391068766269194,
          0.43718427805082966,
          0.42686107015371294,
          0.42142937832333904,
          0.4426879897115292,
          0.4381280532395314,
          0.43277214870129066,
          0.42113301437857587
        ]
      }
    ],
    "threshold": [
      0.5,
      0.7970087121458014,
      0.7844091564554196,
      0.7625829494114857,
      0.7433470452905854,
      0.7637865951080034,
      0.6940274118400376,
      0.6082159378748027,
      0.4580116688396677,
      0.37899830668896156,
      0.3496821871191637,
      0.4030722932659391,
      0.44754879915280976,
      0.42400414591068214,
      0.4185906551933077,
      0.4336249431015812,
      0.4430122412815192,
      0.43026733369131187,
      0.43157827491938083,
      0.4382800511337648,
      0.43342127039482387,
      0.42754620666238613,
      0.4177735466397125,
      0.42015024082910823,
      0.43129560695572017,
      0.4501790297427924,
      0.43755146614348894,
      0.4335797491732146,
      0.43463774914214276,
      0.429007056195842,
      0.43114671745302907,
      0.43353893692739764,
      0.4329663899208686,
      0.43787112504238906,
      0.4328404174567465,
      0.44011578880696833,
      0.44191777293136614,
      0.42356781579837766,
      0.4285146987744168,
      0.433109503913006,
      0.4289835098039974,
      0.4327849662972265,
      0.4447872008170273,
      0.4391068766269194,
      0.43718427805082966,
      0.42686107015371294,
      0.42142937832333904,
      0.4426879897115292,
      0.4381280532395314,
      0.43277214870129066,
      0.42113301437857587
    ]
  },
  "output_dir": "/scratch/users/jdehoney/eqnn_thesis/data/comparisons/eqnn_vs_hea_purestate_50ep_torch_20529347/torch_pure/su2_qcnn/n6/train_size_10/epochs_50/seed_1",
  "parameter_count": 5,
  "runtime_profile": {
    "experiment.build_model": {
      "count": 1,
      "mean_seconds": 0.00027974462136626244,
      "total_seconds": 0.00027974462136626244
    },
    "experiment.build_trainer": {
      "count": 1,
      "mean_seconds": 3.477092832326889e-06,
      "total_seconds": 3.477092832326889e-06
    },
    "experiment.final_test_evaluate": {
      "count": 1,
      "mean_seconds": 0.01754304487258196,
      "total_seconds": 0.01754304487258196
    },
    "experiment.final_train_evaluate": {
      "count": 1,
      "mean_seconds": 0.003322766162455082,
      "total_seconds": 0.003322766162455082
    },
    "experiment.prepare_output_dir": {
      "count": 1,
      "mean_seconds": 0.0010706158354878426,
      "total_seconds": 0.0010706158354878426
    },
    "experiment.test_predict": {
      "count": 1,
      "mean_seconds": 0.03365227812901139,
      "total_seconds": 0.03365227812901139
    },
    "experiment.train_fit": {
      "count": 1,
      "mean_seconds": 2.5510902190580964,
      "total_seconds": 2.5510902190580964
    },
    "experiment.train_predict": {
      "count": 1,
      "mean_seconds": 0.006557784043252468,
      "total_seconds": 0.006557784043252468
    },
    "experiment.write_artifacts": {
      "count": 1,
      "mean_seconds": 0.00982348807156086,
      "total_seconds": 0.00982348807156086
    },
    "train.backward_gradient": {
      "count": 250,
      "mean_seconds": 0.008270676106214523,
      "total_seconds": 2.067669026553631
    },
    "train.epoch_evaluate": {
      "count": 50,
      "mean_seconds": 0.0035230026673525572,
      "total_seconds": 0.17615013336762786
    },
    "train.forward_loss": {
      "count": 53,
      "mean_seconds": 1.3352178458897573e-06,
      "total_seconds": 7.076654583215714e-05
    },
    "train.forward_predict": {
      "count": 53,
      "mean_seconds": 0.006217425144365373,
      "total_seconds": 0.3295235326513648
    },
    "train.initial_evaluate": {
      "count": 1,
      "mean_seconds": 0.1344274627044797,
      "total_seconds": 0.1344274627044797
    },
    "train.optimizer_step": {
      "count": 250,
      "mean_seconds": 6.363276392221451e-05,
      "total_seconds": 0.015908190980553627
    },
    "train.threshold_update": {
      "count": 50,
      "mean_seconds": 0.0027884793374687434,
      "total_seconds": 0.13942396687343717
    }
  },
  "test_metrics": {
    "accuracy": 1.0,
    "loss": 0.11041844027625723
  },
  "train_metrics": {
    "accuracy": 1.0,
    "loss": 0.10686030037347785
  },
  "training_config": {
    "batch_size": 2,
    "beta1": 0.9,
    "beta2": 0.999,
    "classification_threshold": 0.5,
    "epochs": 50,
    "epsilon": 1e-08,
    "finite_difference_eps": 0.001,
    "gradient_backend": "exact",
    "initialization_noise_scale": 0.05,
    "initialization_strategy": "noisy_current",
    "learning_rate": 0.05,
    "loss": "mse",
    "num_restarts": 1,
    "optimizer": "adam",
    "random_seed": 1,
    "restore_best": true,
    "threshold_critical_ratio": 1.0,
    "threshold_update": "paper_nearest_critical"
  }
}
