{
  "classification_threshold": 0.578572234360514,
  "dataset_metadata": {
    "boundary": "open",
    "critical_ratio": 1.0,
    "dataset_name": "bond_alternating_heisenberg_paper_reproduction_v1",
    "dense_test_points_requested": 101,
    "dense_test_points_used": 100,
    "eigensolver_requested": "auto",
    "eigensolver_resolved": "sparse",
    "label_convention": "paper_reproduction_v1_swap_aligned",
    "left_ratio_min": 0.0,
    "notes": [
      "This dataset is locked to the paper_reproduction_v1 protocol.",
      "The training grid is symmetric around the critical ratio so every train set spans both phases.",
      "The dense test grid omits the exact critical point to keep labels unambiguous.",
      "Paper reproduction labels are aligned with the SWAP readout direction: larger outputs map to the trivial phase."
    ],
    "num_qubits": 10,
    "phase_labels": {
      "0": "topological phase (coupling_ratio > critical_ratio)",
      "1": "trivial phase (coupling_ratio < critical_ratio)"
    },
    "protocol": "paper_reproduction_v1",
    "right_ratio_max": 2.0,
    "test_ratios": [
      0.0,
      0.02,
      0.04,
      0.06,
      0.08,
      0.1,
      0.12,
      0.14,
      0.16,
      0.18,
      0.2,
      0.22,
      0.24,
      0.26,
      0.28,
      0.3,
      0.32,
      0.34,
      0.36,
      0.38,
      0.4,
      0.42,
      0.44,
      0.46,
      0.48,
      0.5,
      0.52,
      0.54,
      0.56,
      0.58,
      0.6,
      0.62,
      0.64,
      0.66,
      0.68,
      0.7000000000000001,
      0.72,
      0.74,
      0.76,
      0.78,
      0.8,
      0.8200000000000001,
      0.84,
      0.86,
      0.88,
      0.9,
      0.92,
      0.9400000000000001,
      0.96,
      0.98,
      1.02,
      1.04,
      1.06,
      1.08,
      1.1,
      1.12,
      1.1400000000000001,
      1.16,
      1.18,
      1.2,
      1.22,
      1.24,
      1.26,
      1.28,
      1.3,
      1.32,
      1.34,
      1.36,
      1.3800000000000001,
      1.4000000000000001,
      1.42,
      1.44,
      1.46,
      1.48,
      1.5,
      1.52,
      1.54,
      1.56,
      1.58,
      1.6,
      1.62,
      1.6400000000000001,
      1.6600000000000001,
      1.68,
      1.7,
      1.72,
      1.74,
      1.76,
      1.78,
      1.8,
      1.82,
      1.84,
      1.86,
      1.8800000000000001,
      1.9000000000000001,
      1.92,
      1.94,
      1.96,
      1.98,
      2.0
    ],
    "train_ratios": [
      0.3333333333333333,
      0.6666666666666666,
      1.3333333333333333,
      1.6666666666666665
    ],
    "train_size": 4
  },
  "experiment_config": {
    "boundary": "open",
    "min_readout_qubits": null,
    "model_family": "su2_qcnn",
    "num_qubits": 10,
    "parity_sequence": [
      "even",
      "odd"
    ],
    "pooling_keep": "left",
    "pooling_mode": "partial_trace",
    "readout_mode": "swap",
    "shared_convolution_parameter": true
  },
  "experiment_name": "calibration_su2_qcnn_n10_train4_epochs50_seed0",
  "history": {
    "accuracy": [
      0.5,
      0.0,
      0.0,
      0.0,
      0.25,
      0.25,
      0.25,
      1.0,
      1.0,
      1.0,
      1.0,
      1.0,
      1.0,
      1.0,
      1.0,
      1.0,
      1.0,
      1.0,
      1.0,
      1.0,
      1.0,
      1.0,
      1.0,
      1.0,
      1.0,
      1.0,
      1.0,
      1.0,
      1.0,
      1.0,
      1.0,
      1.0,
      1.0,
      1.0,
      1.0,
      1.0,
      1.0,
      1.0,
      1.0,
      1.0,
      1.0,
      1.0,
      1.0,
      1.0,
      1.0,
      1.0,
      1.0,
      1.0,
      1.0,
      1.0,
      1.0
    ],
    "best_accuracy": 1.0,
    "best_loss": 0.17646280202647924,
    "best_parameters": [
      0.5372170714171784,
      -0.4147731767635354,
      -0.7196981899291244,
      0.4815607308298115,
      -1.4956888139660434,
      0.5855057831550073,
      0.06520000225650686
    ],
    "best_restart": 0,
    "best_threshold": 0.578572234360514,
    "final_parameters": [
      0.5390154811613236,
      -0.4108024323674832,
      -0.7059374365674496,
      0.4751709968654596,
      -1.49899075999111,
      0.5977035911460695,
      0.06520000225650686
    ],
    "final_threshold": 0.5816760234836484,
    "initial_parameters": [
      0.006286511054669665,
      -0.006605243164565094,
      0.032021132522164104,
      0.0052450058576519855,
      -0.02678346865805555,
      0.01807975274547424,
      0.06520000225650686
    ],
    "loss": [
      0.44004001517073665,
      0.40915186236748835,
      0.3634468699947163,
      0.32890818582562287,
      0.3108551791688007,
      0.3086284728940209,
      0.30575762205806456,
      0.28816364287256446,
      0.2629868128295565,
      0.24262609879620486,
      0.2268166496774836,
      0.21339042014627743,
      0.20385823473056136,
      0.20080242389871344,
      0.20180264687862132,
      0.19770138006651722,
      0.1918311515849091,
      0.1887977914077031,
      0.1883438082351297,
      0.18880232237097896,
      0.18504938162195533,
      0.18272038520135175,
      0.18211886335613298,
      0.18088655138562115,
      0.17928657199920567,
      0.17770542652334775,
      0.1783396326882744,
      0.17879501136161846,
      0.17790798901205246,
      0.1770838135749645,
      0.1773878207330772,
      0.17766578589478207,
      0.17714558266080227,
      0.17663608816564746,
      0.1769243849812146,
      0.17703278855440183,
      0.17674181162707447,
      0.17670045013420094,
      0.17675944057937296,
      0.17662903032814625,
      0.1765439118722682,
      0.17658620922311621,
      0.1766261926235895,
      0.17651608245440792,
      0.17651124731802936,
      0.17653458327709934,
      0.1765405708987624,
      0.17646280202647924,
      0.17648629106988034,
      0.17651595580043583,
      0.17647633442710245
    ],
    "restart_histories": [
      {
        "accuracy": [
          0.5,
          0.0,
          0.0,
          0.0,
          0.25,
          0.25,
          0.25,
          1.0,
          1.0,
          1.0,
          1.0,
          1.0,
          1.0,
          1.0,
          1.0,
          1.0,
          1.0,
          1.0,
          1.0,
          1.0,
          1.0,
          1.0,
          1.0,
          1.0,
          1.0,
          1.0,
          1.0,
          1.0,
          1.0,
          1.0,
          1.0,
          1.0,
          1.0,
          1.0,
          1.0,
          1.0,
          1.0,
          1.0,
          1.0,
          1.0,
          1.0,
          1.0,
          1.0,
          1.0,
          1.0,
          1.0,
          1.0,
          1.0,
          1.0,
          1.0,
          1.0
        ],
        "best_accuracy": 1.0,
        "best_loss": 0.17646280202647924,
        "best_parameters": [
          0.5372170714171784,
          -0.4147731767635354,
          -0.7196981899291244,
          0.4815607308298115,
          -1.4956888139660434,
          0.5855057831550073,
          0.06520000225650686
        ],
        "best_threshold": 0.578572234360514,
        "final_parameters": [
          0.5390154811613236,
          -0.4108024323674832,
          -0.7059374365674496,
          0.4751709968654596,
          -1.49899075999111,
          0.5977035911460695,
          0.06520000225650686
        ],
        "final_threshold": 0.5816760234836484,
        "initial_parameters": [
          0.006286511054669665,
          -0.006605243164565094,
          0.032021132522164104,
          0.0052450058576519855,
          -0.02678346865805555,
          0.01807975274547424,
          0.06520000225650686
        ],
        "loss": [
          0.44004001517073665,
          0.40915186236748835,
          0.3634468699947163,
          0.32890818582562287,
          0.3108551791688007,
          0.3086284728940209,
          0.30575762205806456,
          0.28816364287256446,
          0.2629868128295565,
          0.24262609879620486,
          0.2268166496774836,
          0.21339042014627743,
          0.20385823473056136,
          0.20080242389871344,
          0.20180264687862132,
          0.19770138006651722,
          0.1918311515849091,
          0.1887977914077031,
          0.1883438082351297,
          0.18880232237097896,
          0.18504938162195533,
          0.18272038520135175,
          0.18211886335613298,
          0.18088655138562115,
          0.17928657199920567,
          0.17770542652334775,
          0.1783396326882744,
          0.17879501136161846,
          0.17790798901205246,
          0.1770838135749645,
          0.1773878207330772,
          0.17766578589478207,
          0.17714558266080227,
          0.17663608816564746,
          0.1769243849812146,
          0.17703278855440183,
          0.17674181162707447,
          0.17670045013420094,
          0.17675944057937296,
          0.17662903032814625,
          0.1765439118722682,
          0.17658620922311621,
          0.1766261926235895,
          0.17651608245440792,
          0.17651124731802936,
          0.17653458327709934,
          0.1765405708987624,
          0.17646280202647924,
          0.17648629106988034,
          0.17651595580043583,
          0.17647633442710245
        ],
        "threshold": [
          0.5,
          0.8036861049419652,
          0.7793818067589005,
          0.7604592449240453,
          0.7511604838725146,
          0.7515697184127499,
          0.7471481724242705,
          0.7166201056133714,
          0.6593185983853347,
          0.5914487126246997,
          0.5372371621723244,
          0.511978218901641,
          0.5227825970540169,
          0.5466237780287431,
          0.5702865631473166,
          0.5767434369184377,
          0.5790697747809366,
          0.5831483479927579,
          0.5879447167867164,
          0.597018550211198,
          0.5961961452536708,
          0.59350752063453,
          0.5903341538518303,
          0.5850772531898876,
          0.5800572949996028,
          0.5720297943490522,
          0.5682758532532555,
          0.5674696617576815,
          0.5670460321137455,
          0.5711266903555506,
          0.5764190094956325,
          0.579788958383457,
          0.5802722471779189,
          0.5794097144494934,
          0.5777543326637602,
          0.5811030127127456,
          0.5805023694466489,
          0.5840809993543801,
          0.5850424208762008,
          0.5843281251734307,
          0.5831556759356186,
          0.5820868715817611,
          0.57942619593226,
          0.5798604781858361,
          0.5784326174913,
          0.5798396779900863,
          0.58074173272154,
          0.578572234360514,
          0.579254764146454,
          0.578167753418769,
          0.5816760234836484
        ]
      }
    ],
    "threshold": [
      0.5,
      0.8036861049419652,
      0.7793818067589005,
      0.7604592449240453,
      0.7511604838725146,
      0.7515697184127499,
      0.7471481724242705,
      0.7166201056133714,
      0.6593185983853347,
      0.5914487126246997,
      0.5372371621723244,
      0.511978218901641,
      0.5227825970540169,
      0.5466237780287431,
      0.5702865631473166,
      0.5767434369184377,
      0.5790697747809366,
      0.5831483479927579,
      0.5879447167867164,
      0.597018550211198,
      0.5961961452536708,
      0.59350752063453,
      0.5903341538518303,
      0.5850772531898876,
      0.5800572949996028,
      0.5720297943490522,
      0.5682758532532555,
      0.5674696617576815,
      0.5670460321137455,
      0.5711266903555506,
      0.5764190094956325,
      0.579788958383457,
      0.5802722471779189,
      0.5794097144494934,
      0.5777543326637602,
      0.5811030127127456,
      0.5805023694466489,
      0.5840809993543801,
      0.5850424208762008,
      0.5843281251734307,
      0.5831556759356186,
      0.5820868715817611,
      0.57942619593226,
      0.5798604781858361,
      0.5784326174913,
      0.5798396779900863,
      0.58074173272154,
      0.578572234360514,
      0.579254764146454,
      0.578167753418769,
      0.5816760234836484
    ]
  },
  "output_dir": "/scratch/users/jdehoney/eqnn_thesis/data/comparisons/eqnn_vs_hea_50ep_20247287/su2_qcnn/n10/train_size_4/epochs_50/seed_0",
  "parameter_count": 7,
  "runtime_profile": {
    "experiment.build_model": {
      "count": 1,
      "mean_seconds": 0.00015369243919849396,
      "total_seconds": 0.00015369243919849396
    },
    "experiment.build_trainer": {
      "count": 1,
      "mean_seconds": 2.3525208234786987e-06,
      "total_seconds": 2.3525208234786987e-06
    },
    "experiment.final_test_evaluate": {
      "count": 1,
      "mean_seconds": 71.01116114575416,
      "total_seconds": 71.01116114575416
    },
    "experiment.final_train_evaluate": {
      "count": 1,
      "mean_seconds": 2.7671951120719314,
      "total_seconds": 2.7671951120719314
    },
    "experiment.prepare_output_dir": {
      "count": 1,
      "mean_seconds": 0.00034673605114221573,
      "total_seconds": 0.00034673605114221573
    },
    "experiment.test_predict": {
      "count": 1,
      "mean_seconds": 140.3930404894054,
      "total_seconds": 140.3930404894054
    },
    "experiment.train_fit": {
      "count": 1,
      "mean_seconds": 510.4061205275357,
      "total_seconds": 510.4061205275357
    },
    "experiment.train_predict": {
      "count": 1,
      "mean_seconds": 5.66240409296006,
      "total_seconds": 5.66240409296006
    },
    "experiment.write_artifacts": {
      "count": 1,
      "mean_seconds": 0.0049039218574762344,
      "total_seconds": 0.0049039218574762344
    },
    "train.backward_gradient": {
      "count": 100,
      "mean_seconds": 2.996906725410372,
      "total_seconds": 299.6906725410372
    },
    "train.epoch_evaluate": {
      "count": 50,
      "mean_seconds": 2.7753057637624443,
      "total_seconds": 138.7652881881222
    },
    "train.forward_loss": {
      "count": 53,
      "mean_seconds": 1.5276659912658187e-05,
      "total_seconds": 0.0008096629753708839
    },
    "train.forward_predict": {
      "count": 53,
      "mean_seconds": 4.063170555451849,
      "total_seconds": 215.34803943894804
    },
    "train.initial_evaluate": {
      "count": 1,
      "mean_seconds": 2.8075958769768476,
      "total_seconds": 2.8075958769768476
    },
    "train.optimizer_step": {
      "count": 100,
      "mean_seconds": 4.377467557787895e-05,
      "total_seconds": 0.004377467557787895
    },
    "train.threshold_update": {
      "count": 50,
      "mean_seconds": 1.382630889657885,
      "total_seconds": 69.13154448289424
    }
  },
  "test_metrics": {
    "accuracy": 0.98,
    "loss": 0.18348335431901808
  },
  "train_metrics": {
    "accuracy": 1.0,
    "loss": 0.17646280202647924
  },
  "training_config": {
    "batch_size": 2,
    "beta1": 0.9,
    "beta2": 0.999,
    "classification_threshold": 0.5,
    "epochs": 50,
    "epsilon": 1e-08,
    "finite_difference_eps": 0.001,
    "gradient_backend": "exact",
    "initialization_noise_scale": 0.05,
    "initialization_strategy": "noisy_current",
    "learning_rate": 0.05,
    "loss": "mse",
    "num_restarts": 1,
    "optimizer": "adam",
    "random_seed": 0,
    "restore_best": true,
    "threshold_critical_ratio": 1.0,
    "threshold_update": "paper_nearest_critical"
  }
}
