{
  "classification_threshold": 0.4547976679248301,
  "dataset_metadata": {
    "boundary": "open",
    "critical_ratio": 1.0,
    "dataset_name": "bond_alternating_heisenberg_paper_reproduction_v1",
    "dense_test_points_requested": 101,
    "dense_test_points_used": 100,
    "eigensolver_requested": "auto",
    "eigensolver_resolved": "sparse",
    "label_convention": "paper_reproduction_v1_swap_aligned",
    "left_ratio_min": 0.0,
    "notes": [
      "This dataset is locked to the paper_reproduction_v1 protocol.",
      "The training grid is symmetric around the critical ratio so every train set spans both phases.",
      "The dense test grid omits the exact critical point to keep labels unambiguous.",
      "Paper reproduction labels are aligned with the SWAP readout direction: larger outputs map to the trivial phase."
    ],
    "num_qubits": 8,
    "phase_labels": {
      "0": "topological phase (coupling_ratio > critical_ratio)",
      "1": "trivial phase (coupling_ratio < critical_ratio)"
    },
    "protocol": "paper_reproduction_v1",
    "right_ratio_max": 2.0,
    "test_ratios": [
      0.0,
      0.02,
      0.04,
      0.06,
      0.08,
      0.1,
      0.12,
      0.14,
      0.16,
      0.18,
      0.2,
      0.22,
      0.24,
      0.26,
      0.28,
      0.3,
      0.32,
      0.34,
      0.36,
      0.38,
      0.4,
      0.42,
      0.44,
      0.46,
      0.48,
      0.5,
      0.52,
      0.54,
      0.56,
      0.58,
      0.6,
      0.62,
      0.64,
      0.66,
      0.68,
      0.7000000000000001,
      0.72,
      0.74,
      0.76,
      0.78,
      0.8,
      0.8200000000000001,
      0.84,
      0.86,
      0.88,
      0.9,
      0.92,
      0.9400000000000001,
      0.96,
      0.98,
      1.02,
      1.04,
      1.06,
      1.08,
      1.1,
      1.12,
      1.1400000000000001,
      1.16,
      1.18,
      1.2,
      1.22,
      1.24,
      1.26,
      1.28,
      1.3,
      1.32,
      1.34,
      1.36,
      1.3800000000000001,
      1.4000000000000001,
      1.42,
      1.44,
      1.46,
      1.48,
      1.5,
      1.52,
      1.54,
      1.56,
      1.58,
      1.6,
      1.62,
      1.6400000000000001,
      1.6600000000000001,
      1.68,
      1.7,
      1.72,
      1.74,
      1.76,
      1.78,
      1.8,
      1.82,
      1.84,
      1.86,
      1.8800000000000001,
      1.9000000000000001,
      1.92,
      1.94,
      1.96,
      1.98,
      2.0
    ],
    "train_ratios": [
      0.2,
      0.4,
      0.6000000000000001,
      0.8,
      1.2,
      1.4,
      1.6,
      1.8
    ],
    "train_size": 8
  },
  "experiment_config": {
    "backend_name": "torch_pure",
    "boundary": "open",
    "min_readout_qubits": null,
    "model_family": "su2_qcnn",
    "num_qubits": 8,
    "parity_sequence": [
      "even",
      "odd"
    ],
    "pooling_keep": "left",
    "pooling_mode": "partial_trace",
    "readout_mode": "swap",
    "shared_convolution_parameter": true
  },
  "experiment_name": "calibration_su2_qcnn_torch_pure_n8_train8_epochs50_seed2",
  "history": {
    "accuracy": [
      0.5,
      0.0,
      0.375,
      0.75,
      1.0,
      1.0,
      1.0,
      1.0,
      1.0,
      1.0,
      1.0,
      1.0,
      1.0,
      1.0,
      1.0,
      1.0,
      1.0,
      1.0,
      1.0,
      1.0,
      1.0,
      1.0,
      1.0,
      1.0,
      1.0,
      1.0,
      1.0,
      1.0,
      1.0,
      1.0,
      1.0,
      1.0,
      1.0,
      1.0,
      1.0,
      1.0,
      1.0,
      1.0,
      1.0,
      1.0,
      1.0,
      1.0,
      1.0,
      1.0,
      1.0,
      1.0,
      1.0,
      1.0,
      1.0,
      1.0,
      1.0
    ],
    "best_accuracy": 1.0,
    "best_loss": 0.17923489591231132,
    "best_parameters": [
      -0.6672449623625788,
      0.3135031238982321,
      0.581485026562905,
      -1.3840827166091834,
      0.08998536942706825
    ],
    "best_restart": 0,
    "best_threshold": 0.4547976679248301,
    "final_parameters": [
      -0.6734987525655562,
      0.2958250405831152,
      0.5787160264298215,
      -1.3914941929730928,
      0.08998536934524415
    ],
    "final_threshold": 0.46212779545408234,
    "initial_parameters": [
      0.009452669089676654,
      -0.02613742207403737,
      -0.020653177169594673,
      -0.12207336913199279,
      0.0899853691360451
    ],
    "loss": [
      0.4332659706609881,
      0.37792518290967414,
      0.3179945726151133,
      0.29782862274554933,
      0.25014610675899873,
      0.208686298892348,
      0.1968561647656536,
      0.19604275368194846,
      0.1944113999339802,
      0.19323230213011827,
      0.191750423987276,
      0.185857459678972,
      0.1827144256915424,
      0.18142984018991715,
      0.1810836956295935,
      0.18137400314986718,
      0.18096878772560338,
      0.1809643041018245,
      0.18055610108474487,
      0.18004885367206025,
      0.17981738914535775,
      0.17982428763519204,
      0.1796575717506026,
      0.17963479980217453,
      0.17952253689076286,
      0.17952242065647428,
      0.17939615093421868,
      0.1794971128668204,
      0.17933848416000683,
      0.17964570814266917,
      0.1793256362307798,
      0.17928596672817398,
      0.17932368678317243,
      0.1792562188630621,
      0.17935761683154713,
      0.17937072812232518,
      0.17924594779644404,
      0.17923489591231132,
      0.17924844519689268,
      0.17925165411055327,
      0.17952192410053103,
      0.17994177786162277,
      0.17933854203959818,
      0.17930425918404652,
      0.1792720200222277,
      0.17926224554026346,
      0.17953458571036418,
      0.17974822472824123,
      0.17967549147474296,
      0.1792379673387116,
      0.1793427879650102
    ],
    "restart_histories": [
      {
        "accuracy": [
          0.5,
          0.0,
          0.375,
          0.75,
          1.0,
          1.0,
          1.0,
          1.0,
          1.0,
          1.0,
          1.0,
          1.0,
          1.0,
          1.0,
          1.0,
          1.0,
          1.0,
          1.0,
          1.0,
          1.0,
          1.0,
          1.0,
          1.0,
          1.0,
          1.0,
          1.0,
          1.0,
          1.0,
          1.0,
          1.0,
          1.0,
          1.0,
          1.0,
          1.0,
          1.0,
          1.0,
          1.0,
          1.0,
          1.0,
          1.0,
          1.0,
          1.0,
          1.0,
          1.0,
          1.0,
          1.0,
          1.0,
          1.0,
          1.0,
          1.0,
          1.0
        ],
        "best_accuracy": 1.0,
        "best_loss": 0.17923489591231132,
        "best_parameters": [
          -0.6672449623625788,
          0.3135031238982321,
          0.581485026562905,
          -1.3840827166091834,
          0.08998536942706825
        ],
        "best_threshold": 0.4547976679248301,
        "final_parameters": [
          -0.6734987525655562,
          0.2958250405831152,
          0.5787160264298215,
          -1.3914941929730928,
          0.08998536934524415
        ],
        "final_threshold": 0.46212779545408234,
        "initial_parameters": [
          0.009452669089676654,
          -0.02613742207403737,
          -0.020653177169594673,
          -0.12207336913199279,
          0.0899853691360451
        ],
        "loss": [
          0.4332659706609881,
          0.37792518290967414,
          0.3179945726151133,
          0.29782862274554933,
          0.25014610675899873,
          0.208686298892348,
          0.1968561647656536,
          0.19604275368194846,
          0.1944113999339802,
          0.19323230213011827,
          0.191750423987276,
          0.185857459678972,
          0.1827144256915424,
          0.18142984018991715,
          0.1810836956295935,
          0.18137400314986718,
          0.18096878772560338,
          0.1809643041018245,
          0.18055610108474487,
          0.18004885367206025,
          0.17981738914535775,
          0.17982428763519204,
          0.1796575717506026,
          0.17963479980217453,
          0.17952253689076286,
          0.17952242065647428,
          0.17939615093421868,
          0.1794971128668204,
          0.17933848416000683,
          0.17964570814266917,
          0.1793256362307798,
          0.17928596672817398,
          0.17932368678317243,
          0.1792562188630621,
          0.17935761683154713,
          0.17937072812232518,
          0.17924594779644404,
          0.17923489591231132,
          0.17924844519689268,
          0.17925165411055327,
          0.17952192410053103,
          0.17994177786162277,
          0.17933854203959818,
          0.17930425918404652,
          0.1792720200222277,
          0.17926224554026346,
          0.17953458571036418,
          0.17974822472824123,
          0.17967549147474296,
          0.1792379673387116,
          0.1793427879650102
        ],
        "threshold": [
          0.5,
          0.810129386019456,
          0.7633892093948651,
          0.752877444171417,
          0.6865590822451627,
          0.5807972777471578,
          0.5081632081463177,
          0.4649443299866206,
          0.4598887105656323,
          0.4937012658317372,
          0.5011920714220701,
          0.4745213390226044,
          0.45972464228750065,
          0.45871507703190545,
          0.4654190504275865,
          0.47564458082213157,
          0.45262070056985976,
          0.4521811637372619,
          0.46591295273052535,
          0.46369371304434215,
          0.4572159487520827,
          0.458926595900632,
          0.44857934583970416,
          0.448089330084395,
          0.4560568319091396,
          0.4478381796745989,
          0.45436211643286006,
          0.4449153092229803,
          0.4555405996263031,
          0.4674475771530708,
          0.45881188384238125,
          0.4534599755706306,
          0.4598802574959341,
          0.45608795470875063,
          0.44608194899868586,
          0.44584149599880174,
          0.45505345591237045,
          0.4547976679248301,
          0.454741513386011,
          0.4562017468040832,
          0.46695375998873473,
          0.47391517041674147,
          0.46192497587522974,
          0.4605541779264567,
          0.4588735877857597,
          0.4511676616610657,
          0.44146288217238916,
          0.4372007010310975,
          0.4383974377190416,
          0.4531082064775184,
          0.46212779545408234
        ]
      }
    ],
    "threshold": [
      0.5,
      0.810129386019456,
      0.7633892093948651,
      0.752877444171417,
      0.6865590822451627,
      0.5807972777471578,
      0.5081632081463177,
      0.4649443299866206,
      0.4598887105656323,
      0.4937012658317372,
      0.5011920714220701,
      0.4745213390226044,
      0.45972464228750065,
      0.45871507703190545,
      0.4654190504275865,
      0.47564458082213157,
      0.45262070056985976,
      0.4521811637372619,
      0.46591295273052535,
      0.46369371304434215,
      0.4572159487520827,
      0.458926595900632,
      0.44857934583970416,
      0.448089330084395,
      0.4560568319091396,
      0.4478381796745989,
      0.45436211643286006,
      0.4449153092229803,
      0.4555405996263031,
      0.4674475771530708,
      0.45881188384238125,
      0.4534599755706306,
      0.4598802574959341,
      0.45608795470875063,
      0.44608194899868586,
      0.44584149599880174,
      0.45505345591237045,
      0.4547976679248301,
      0.454741513386011,
      0.4562017468040832,
      0.46695375998873473,
      0.47391517041674147,
      0.46192497587522974,
      0.4605541779264567,
      0.4588735877857597,
      0.4511676616610657,
      0.44146288217238916,
      0.4372007010310975,
      0.4383974377190416,
      0.4531082064775184,
      0.46212779545408234
    ]
  },
  "output_dir": "/scratch/users/jdehoney/eqnn_thesis/data/comparisons/eqnn_vs_hea_purestate_50ep_torch_20529347/torch_pure/su2_qcnn/n8/train_size_8/epochs_50/seed_2",
  "parameter_count": 5,
  "runtime_profile": {
    "experiment.build_model": {
      "count": 1,
      "mean_seconds": 0.00014408864080905914,
      "total_seconds": 0.00014408864080905914
    },
    "experiment.build_trainer": {
      "count": 1,
      "mean_seconds": 2.473592758178711e-06,
      "total_seconds": 2.473592758178711e-06
    },
    "experiment.final_test_evaluate": {
      "count": 1,
      "mean_seconds": 0.2257632538676262,
      "total_seconds": 0.2257632538676262
    },
    "experiment.final_train_evaluate": {
      "count": 1,
      "mean_seconds": 0.021880741231143475,
      "total_seconds": 0.021880741231143475
    },
    "experiment.prepare_output_dir": {
      "count": 1,
      "mean_seconds": 0.0003393935039639473,
      "total_seconds": 0.0003393935039639473
    },
    "experiment.test_predict": {
      "count": 1,
      "mean_seconds": 0.4441359844058752,
      "total_seconds": 0.4441359844058752
    },
    "experiment.train_fit": {
      "count": 1,
      "mean_seconds": 6.308056668378413,
      "total_seconds": 6.308056668378413
    },
    "experiment.train_predict": {
      "count": 1,
      "mean_seconds": 0.03759399987757206,
      "total_seconds": 0.03759399987757206
    },
    "experiment.write_artifacts": {
      "count": 1,
      "mean_seconds": 0.005183020606637001,
      "total_seconds": 0.005183020606637001
    },
    "train.backward_gradient": {
      "count": 200,
      "mean_seconds": 0.02319227857980877,
      "total_seconds": 4.638455715961754
    },
    "train.epoch_evaluate": {
      "count": 50,
      "mean_seconds": 0.021421637926250695,
      "total_seconds": 1.0710818963125348
    },
    "train.forward_loss": {
      "count": 53,
      "mean_seconds": 6.982107769768193e-07,
      "total_seconds": 3.700517117977142e-05
    },
    "train.forward_predict": {
      "count": 53,
      "mean_seconds": 0.027403748471219586,
      "total_seconds": 1.452398668974638
    },
    "train.initial_evaluate": {
      "count": 1,
      "mean_seconds": 0.1349736424162984,
      "total_seconds": 0.1349736424162984
    },
    "train.optimizer_step": {
      "count": 200,
      "mean_seconds": 6.801136303693056e-05,
      "total_seconds": 0.013602272607386112
    },
    "train.threshold_update": {
      "count": 50,
      "mean_seconds": 0.00869156764820218,
      "total_seconds": 0.43457838241010904
    }
  },
  "test_metrics": {
    "accuracy": 0.99,
    "loss": 0.18082060556172683
  },
  "train_metrics": {
    "accuracy": 1.0,
    "loss": 0.17923489591231132
  },
  "training_config": {
    "batch_size": 2,
    "beta1": 0.9,
    "beta2": 0.999,
    "classification_threshold": 0.5,
    "epochs": 50,
    "epsilon": 1e-08,
    "finite_difference_eps": 0.001,
    "gradient_backend": "exact",
    "initialization_noise_scale": 0.05,
    "initialization_strategy": "noisy_current",
    "learning_rate": 0.05,
    "loss": "mse",
    "num_restarts": 1,
    "optimizer": "adam",
    "random_seed": 2,
    "restore_best": true,
    "threshold_critical_ratio": 1.0,
    "threshold_update": "paper_nearest_critical"
  }
}
