{
  "classification_threshold": 0.4200837783916744,
  "dataset_metadata": {
    "boundary": "open",
    "critical_ratio": 1.0,
    "dataset_name": "bond_alternating_heisenberg_paper_reproduction_v1",
    "dense_test_points_requested": 101,
    "dense_test_points_used": 100,
    "eigensolver_requested": "auto",
    "eigensolver_resolved": "sparse",
    "label_convention": "paper_reproduction_v1_swap_aligned",
    "left_ratio_min": 0.0,
    "notes": [
      "This dataset is locked to the paper_reproduction_v1 protocol.",
      "The training grid is symmetric around the critical ratio so every train set spans both phases.",
      "The dense test grid omits the exact critical point to keep labels unambiguous.",
      "Paper reproduction labels are aligned with the SWAP readout direction: larger outputs map to the trivial phase."
    ],
    "num_qubits": 12,
    "phase_labels": {
      "0": "topological phase (coupling_ratio > critical_ratio)",
      "1": "trivial phase (coupling_ratio < critical_ratio)"
    },
    "protocol": "paper_reproduction_v1",
    "right_ratio_max": 2.0,
    "test_ratios": [
      0.0,
      0.02,
      0.04,
      0.06,
      0.08,
      0.1,
      0.12,
      0.14,
      0.16,
      0.18,
      0.2,
      0.22,
      0.24,
      0.26,
      0.28,
      0.3,
      0.32,
      0.34,
      0.36,
      0.38,
      0.4,
      0.42,
      0.44,
      0.46,
      0.48,
      0.5,
      0.52,
      0.54,
      0.56,
      0.58,
      0.6,
      0.62,
      0.64,
      0.66,
      0.68,
      0.7000000000000001,
      0.72,
      0.74,
      0.76,
      0.78,
      0.8,
      0.8200000000000001,
      0.84,
      0.86,
      0.88,
      0.9,
      0.92,
      0.9400000000000001,
      0.96,
      0.98,
      1.02,
      1.04,
      1.06,
      1.08,
      1.1,
      1.12,
      1.1400000000000001,
      1.16,
      1.18,
      1.2,
      1.22,
      1.24,
      1.26,
      1.28,
      1.3,
      1.32,
      1.34,
      1.36,
      1.3800000000000001,
      1.4000000000000001,
      1.42,
      1.44,
      1.46,
      1.48,
      1.5,
      1.52,
      1.54,
      1.56,
      1.58,
      1.6,
      1.62,
      1.6400000000000001,
      1.6600000000000001,
      1.68,
      1.7,
      1.72,
      1.74,
      1.76,
      1.78,
      1.8,
      1.82,
      1.84,
      1.86,
      1.8800000000000001,
      1.9000000000000001,
      1.92,
      1.94,
      1.96,
      1.98,
      2.0
    ],
    "train_ratios": [
      0.25,
      0.5,
      0.75,
      1.25,
      1.5,
      1.75
    ],
    "train_size": 6
  },
  "experiment_config": {
    "boundary": "open",
    "min_readout_qubits": null,
    "model_family": "su2_qcnn",
    "num_qubits": 12,
    "parity_sequence": [
      "even",
      "odd"
    ],
    "pooling_keep": "left",
    "pooling_mode": "partial_trace",
    "readout_mode": "swap",
    "shared_convolution_parameter": true
  },
  "experiment_name": "calibration_su2_qcnn_n12_train6_epochs50_seed1",
  "history": {
    "accuracy": [
      0.5,
      0.0,
      0.0,
      0.6666666666666666,
      1.0,
      1.0,
      1.0,
      1.0,
      1.0,
      1.0,
      1.0,
      1.0,
      1.0,
      1.0,
      1.0,
      1.0,
      1.0,
      0.8333333333333334,
      0.8333333333333334,
      0.8333333333333334,
      1.0,
      1.0,
      1.0,
      1.0,
      1.0,
      1.0,
      1.0,
      1.0,
      1.0,
      1.0,
      1.0,
      1.0,
      1.0,
      1.0,
      1.0,
      1.0,
      1.0,
      1.0,
      1.0,
      1.0,
      1.0,
      1.0,
      1.0,
      1.0,
      1.0,
      1.0,
      1.0,
      1.0,
      1.0,
      1.0,
      1.0
    ],
    "best_accuracy": 1.0,
    "best_loss": 0.14945266778265226,
    "best_parameters": [
      0.7344342404358848,
      -0.17134433649539801,
      -1.0645632451069256,
      1.3940909275703695,
      -0.6113074688658501,
      0.5810709692398631,
      -0.026847661768014258
    ],
    "best_restart": 0,
    "best_threshold": 0.4200837783916744,
    "final_parameters": [
      0.7294270483975819,
      -0.17585342241462776,
      -1.0695780940582928,
      1.3952006691424308,
      -0.593331914269685,
      0.5943826001934309,
      -0.026847661768014258
    ],
    "final_threshold": 0.4145213195456115,
    "initial_parameters": [
      0.017279209603239302,
      0.04108090717505792,
      0.016521853809169356,
      -0.06515786158021805,
      0.04526779333365589,
      0.022318728618200567,
      -0.026847661768014258
    ],
    "loss": [
      0.3989821424775994,
      0.3729163376261167,
      0.32614496532113746,
      0.311359338493316,
      0.2892084692218074,
      0.2631633777577374,
      0.24125274485792336,
      0.22739297525456134,
      0.21826411110692545,
      0.20906141200495512,
      0.20328003679679496,
      0.20091116484228952,
      0.1996608237882629,
      0.1976366503341923,
      0.1946377624825716,
      0.1929178455364645,
      0.18619362753801383,
      0.1802141179997119,
      0.17372573134272865,
      0.16606313328889802,
      0.15949398866811929,
      0.15340001231328448,
      0.1511711447247651,
      0.15132018911624726,
      0.15112118748482717,
      0.15139681872233812,
      0.15126771702399963,
      0.15095387294922666,
      0.15084032857241916,
      0.14980569935047702,
      0.14959534907105443,
      0.14980925855881758,
      0.14957128049270663,
      0.14962243869030542,
      0.14958031172871042,
      0.14960687035840478,
      0.14961493431683873,
      0.14948198688871042,
      0.149535744869887,
      0.14951276674300096,
      0.14949578920676695,
      0.14970007122888024,
      0.14950950165663626,
      0.14966147527751936,
      0.14951382484195966,
      0.14947486264513574,
      0.1494634428995539,
      0.14945266778265226,
      0.1495355034832652,
      0.1496037626012914,
      0.1495003094700014
    ],
    "restart_histories": [
      {
        "accuracy": [
          0.5,
          0.0,
          0.0,
          0.6666666666666666,
          1.0,
          1.0,
          1.0,
          1.0,
          1.0,
          1.0,
          1.0,
          1.0,
          1.0,
          1.0,
          1.0,
          1.0,
          1.0,
          0.8333333333333334,
          0.8333333333333334,
          0.8333333333333334,
          1.0,
          1.0,
          1.0,
          1.0,
          1.0,
          1.0,
          1.0,
          1.0,
          1.0,
          1.0,
          1.0,
          1.0,
          1.0,
          1.0,
          1.0,
          1.0,
          1.0,
          1.0,
          1.0,
          1.0,
          1.0,
          1.0,
          1.0,
          1.0,
          1.0,
          1.0,
          1.0,
          1.0,
          1.0,
          1.0,
          1.0
        ],
        "best_accuracy": 1.0,
        "best_loss": 0.14945266778265226,
        "best_parameters": [
          0.7344342404358848,
          -0.17134433649539801,
          -1.0645632451069256,
          1.3940909275703695,
          -0.6113074688658501,
          0.5810709692398631,
          -0.026847661768014258
        ],
        "best_threshold": 0.4200837783916744,
        "final_parameters": [
          0.7294270483975819,
          -0.17585342241462776,
          -1.0695780940582928,
          1.3952006691424308,
          -0.593331914269685,
          0.5943826001934309,
          -0.026847661768014258
        ],
        "final_threshold": 0.4145213195456115,
        "initial_parameters": [
          0.017279209603239302,
          0.04108090717505792,
          0.016521853809169356,
          -0.06515786158021805,
          0.04526779333365589,
          0.022318728618200567,
          -0.026847661768014258
        ],
        "loss": [
          0.3989821424775994,
          0.3729163376261167,
          0.32614496532113746,
          0.311359338493316,
          0.2892084692218074,
          0.2631633777577374,
          0.24125274485792336,
          0.22739297525456134,
          0.21826411110692545,
          0.20906141200495512,
          0.20328003679679496,
          0.20091116484228952,
          0.1996608237882629,
          0.1976366503341923,
          0.1946377624825716,
          0.1929178455364645,
          0.18619362753801383,
          0.1802141179997119,
          0.17372573134272865,
          0.16606313328889802,
          0.15949398866811929,
          0.15340001231328448,
          0.1511711447247651,
          0.15132018911624726,
          0.15112118748482717,
          0.15139681872233812,
          0.15126771702399963,
          0.15095387294922666,
          0.15084032857241916,
          0.14980569935047702,
          0.14959534907105443,
          0.14980925855881758,
          0.14957128049270663,
          0.14962243869030542,
          0.14958031172871042,
          0.14960687035840478,
          0.14961493431683873,
          0.14948198688871042,
          0.149535744869887,
          0.14951276674300096,
          0.14949578920676695,
          0.14970007122888024,
          0.14950950165663626,
          0.14966147527751936,
          0.14951382484195966,
          0.14947486264513574,
          0.1494634428995539,
          0.14945266778265226,
          0.1495355034832652,
          0.1496037626012914,
          0.1495003094700014
        ],
        "threshold": [
          0.5,
          0.7952844011704809,
          0.7605266278280701,
          0.7542637697776801,
          0.7407224058109831,
          0.6995049853085387,
          0.649928404484733,
          0.6160259678384594,
          0.5885664776505994,
          0.5516333622080976,
          0.5275640664010445,
          0.499680327923698,
          0.4810245013016583,
          0.48180017271259745,
          0.4738290573068809,
          0.48837716709360735,
          0.4696893480891783,
          0.43277002652869334,
          0.4348749637111486,
          0.42162509186125136,
          0.4348843649337643,
          0.43238593470925085,
          0.43632176522464194,
          0.4419967504112732,
          0.4346853052512373,
          0.4280967229723226,
          0.41454298565416586,
          0.41091987558804144,
          0.40276338298432945,
          0.417816048573579,
          0.42294288875005315,
          0.43107981440535365,
          0.42284027856644324,
          0.4141954236055895,
          0.4218438235126596,
          0.42434743162215827,
          0.42656858461648467,
          0.4218583185520137,
          0.4266611593878742,
          0.4154682571131435,
          0.423023679603158,
          0.4313571510312749,
          0.4249710532802129,
          0.4116197920011477,
          0.4165458869002484,
          0.4223933644042082,
          0.4186307093205451,
          0.4200837783916744,
          0.413665792515001,
          0.41102674727571176,
          0.4145213195456115
        ]
      }
    ],
    "threshold": [
      0.5,
      0.7952844011704809,
      0.7605266278280701,
      0.7542637697776801,
      0.7407224058109831,
      0.6995049853085387,
      0.649928404484733,
      0.6160259678384594,
      0.5885664776505994,
      0.5516333622080976,
      0.5275640664010445,
      0.499680327923698,
      0.4810245013016583,
      0.48180017271259745,
      0.4738290573068809,
      0.48837716709360735,
      0.4696893480891783,
      0.43277002652869334,
      0.4348749637111486,
      0.42162509186125136,
      0.4348843649337643,
      0.43238593470925085,
      0.43632176522464194,
      0.4419967504112732,
      0.4346853052512373,
      0.4280967229723226,
      0.41454298565416586,
      0.41091987558804144,
      0.40276338298432945,
      0.417816048573579,
      0.42294288875005315,
      0.43107981440535365,
      0.42284027856644324,
      0.4141954236055895,
      0.4218438235126596,
      0.42434743162215827,
      0.42656858461648467,
      0.4218583185520137,
      0.4266611593878742,
      0.4154682571131435,
      0.423023679603158,
      0.4313571510312749,
      0.4249710532802129,
      0.4116197920011477,
      0.4165458869002484,
      0.4223933644042082,
      0.4186307093205451,
      0.4200837783916744,
      0.413665792515001,
      0.41102674727571176,
      0.4145213195456115
    ]
  },
  "output_dir": "/scratch/users/jdehoney/eqnn_thesis/data/comparisons/eqnn_vs_hea_50ep_20247287/su2_qcnn/n12/train_size_6/epochs_50/seed_1",
  "parameter_count": 7,
  "runtime_profile": {
    "experiment.build_model": {
      "count": 1,
      "mean_seconds": 0.00033767614513635635,
      "total_seconds": 0.00033767614513635635
    },
    "experiment.build_trainer": {
      "count": 1,
      "mean_seconds": 4.828907549381256e-06,
      "total_seconds": 4.828907549381256e-06
    },
    "experiment.final_test_evaluate": {
      "count": 1,
      "mean_seconds": 3155.7753107007593,
      "total_seconds": 3155.7753107007593
    },
    "experiment.final_train_evaluate": {
      "count": 1,
      "mean_seconds": 189.66934135276824,
      "total_seconds": 189.66934135276824
    },
    "experiment.prepare_output_dir": {
      "count": 1,
      "mean_seconds": 0.009452852420508862,
      "total_seconds": 0.009452852420508862
    },
    "experiment.test_predict": {
      "count": 1,
      "mean_seconds": 6308.702147837728,
      "total_seconds": 6308.702147837728
    },
    "experiment.train_fit": {
      "count": 1,
      "mean_seconds": 34377.25001213141,
      "total_seconds": 34377.25001213141
    },
    "experiment.train_predict": {
      "count": 1,
      "mean_seconds": 378.1255783289671,
      "total_seconds": 378.1255783289671
    },
    "experiment.write_artifacts": {
      "count": 1,
      "mean_seconds": 0.00904044508934021,
      "total_seconds": 0.00904044508934021
    },
    "train.backward_gradient": {
      "count": 150,
      "mean_seconds": 143.9883830843804,
      "total_seconds": 21598.257462657057
    },
    "train.epoch_evaluate": {
      "count": 50,
      "mean_seconds": 188.90058934874833,
      "total_seconds": 9445.029467437416
    },
    "train.forward_loss": {
      "count": 53,
      "mean_seconds": 0.00010014204132669377,
      "total_seconds": 0.00530752819031477
    },
    "train.forward_predict": {
      "count": 53,
      "mean_seconds": 244.90752144567318,
      "total_seconds": 12980.098636620678
    },
    "train.initial_evaluate": {
      "count": 1,
      "mean_seconds": 189.6652882192284,
      "total_seconds": 189.6652882192284
    },
    "train.optimizer_step": {
      "count": 150,
      "mean_seconds": 0.00012269307548801105,
      "total_seconds": 0.018403961323201656
    },
    "train.threshold_update": {
      "count": 50,
      "mean_seconds": 62.88406285889447,
      "total_seconds": 3144.2031429447234
    }
  },
  "test_metrics": {
    "accuracy": 0.98,
    "loss": 0.1566435054423035
  },
  "train_metrics": {
    "accuracy": 1.0,
    "loss": 0.14945266778265226
  },
  "training_config": {
    "batch_size": 2,
    "beta1": 0.9,
    "beta2": 0.999,
    "classification_threshold": 0.5,
    "epochs": 50,
    "epsilon": 1e-08,
    "finite_difference_eps": 0.001,
    "gradient_backend": "exact",
    "initialization_noise_scale": 0.05,
    "initialization_strategy": "noisy_current",
    "learning_rate": 0.05,
    "loss": "mse",
    "num_restarts": 1,
    "optimizer": "adam",
    "random_seed": 1,
    "restore_best": true,
    "threshold_critical_ratio": 1.0,
    "threshold_update": "paper_nearest_critical"
  }
}
